{
  "device": "openaps://edison", 
  "pump": {
    "battery": {
      "status": "normal", 
      "voltage": 1.46
    }, 
    "status": {
      "status": "normal", 
      "timestamp": "2016-06-04T18:37:56.000Z", 
      "bolusing": false, 
      "suspended": false
    }, 
    "reservoir": 96.9, 
    "clock": "2016-06-04T14:38:26-04:00"
  }, 
  "openaps": {
    "suggested": {
      "bg": 135, 
      "temp": "absolute", 
      "snoozeBG": 107, 
      "timestamp": "2016-06-04T18:38:06.000Z", 
      "rate": 1.25, 
      "reason": "Eventual BG 107>=95, temp 0.85<1.25U/hr", 
      "eventualBG": 107, 
      "duration": 30, 
      "mealAssist": "Off: Carbs: undefined Boluses: undefined ISF: 40, Target: 95 Deviation: 1 BGI: -0.68", 
      "tick": "+1"
    }, 
    "iob": {
      "netbasalinsulin": 0.4, 
      "timestamp": "2016-06-04T18:38:01.000Z", 
      "activity": 0.0034, 
      "basaliob": 0.714, 
      "hightempinsulin": 1, 
      "bolussnooze": 0, 
      "iob": 0.714
    }, 
    "enacted": {
      "bg": 135, 
      "temp": "absolute", 
      "snoozeBG": 107, 
      "recieved": true, 
      "reason": "Eventual BG 107>=95, temp 0.85<1.25U/hr", 
      "rate": 1.25, 
      "eventualBG": 107, 
      "timestamp": "2016-06-04T18:38:10.000Z", 
      "duration": 30, 
      "mealAssist": "Off: Carbs: undefined Boluses: undefined ISF: 40, Target: 95 Deviation: 1 BGI: -0.68", 
      "tick": "+1"
    }
  }
}