{
  "device": "openaps://edison", 
  "pump": {
    "battery": {
      "status": "normal", 
      "voltage": 1.53
    }, 
    "status": {
      "status": "normal", 
      "timestamp": "2016-07-13T17:13:48.000Z", 
      "bolusing": false, 
      "suspended": false
    }, 
    "reservoir": 128.7, 
    "clock": "2016-07-13T13:13:09-04:00"
  }, 
  "openaps": {
    "suggested": {
      "bg": 144, 
      "temp": "absolute", 
      "snoozeBG": 56, 
      "timestamp": "2016-07-13T17:13:58.000Z", 
      "rate": 0, 
      "reason": "Eventual BG 2<105, Snooze BG 56, setting -0.82U/hr. Setting neutral temp basal of 0U/hr", 
      "eventualBG": 2, 
      "duration": 30, 
      "mealAssist": "Off: Carbs: undefined Boluses: undefined ISF: 35, Target: 105 Deviation: 26 BGI: -9.68", 
      "tick": -1
    }, 
    "iob": {
      "netbasalinsulin": 2.25, 
      "timestamp": "2016-07-13T17:13:52.000Z", 
      "activity": 0.0553, 
      "basaliob": 1.379, 
      "hightempinsulin": 2.25, 
      "bolussnooze": 1.037, 
      "iob": 4.792
    }, 
    "enacted": {
      "bg": 144, 
      "temp": "absolute", 
      "snoozeBG": 56, 
      "recieved": true, 
      "reason": "Eventual BG 2<105, Snooze BG 56, setting -0.82U/hr. Setting neutral temp basal of 0U/hr", 
      "rate": 0, 
      "eventualBG": 2, 
      "timestamp": "2016-07-13T17:14:03.000Z", 
      "duration": 30, 
      "mealAssist": "Off: Carbs: undefined Boluses: undefined ISF: 35, Target: 105 Deviation: 26 BGI: -9.68", 
      "tick": -1
    }
  }
}